package_archetype/__init__.py
package_archetype/hello_world.py
package_archetype/test/__init__.py
processingpy-0.1.dist-info/LICENSE
processingpy-0.1.dist-info/METADATA
processingpy-0.1.dist-info/WHEEL
processingpy-0.1.dist-info/entry_points.txt
processingpy-0.1.dist-info/top_level.txt
processingpy-0.1.dist-info/RECORD
